numbers_to_letters/__init__.py
numbers_to_letters/transform_number.py
numbers_to_letters-1.0.0.dist-info/METADATA
numbers_to_letters-1.0.0.dist-info/WHEEL
numbers_to_letters-1.0.0.dist-info/top_level.txt
numbers_to_letters-1.0.0.dist-info/RECORD
