Metadata-Version: 2.1
Name: numbers-to-letters
Version: 1.0.0
Summary: convert numbers int or float to letters
Home-page: UNKNOWN
Author: Reyes2777
Author-email: jonathan.reyes2777@gmail.com
License: MIT
Platform: UNKNOWN
